[
	{
		"ref" : "TB",
		"charges" : [{"ref" : "RA", "variation" : 0}, {"ref" : "RB", "variation" : 1}],
		"produits" : [{"ref" : "TA", "variation" : 0}],
		"type" : "MAR"
	},

	{
		"ref" : "TG",
		"charges" : [{"ref" : "RC", "variation" : 0}, {"ref" : "RD", "variation" : 1}],
		"produits" : [
						{"ref" : "TC", "variation" : 0},
						{"ref" : "TD", "variation" : 0},
						{"ref" : "TE", "variation" : 0},
						{"ref" : "TF", "variation" : 0}
					],
		"type" : "MAR"
	},

	{
		"ref" : "TI",
		"charges" : [],
		"produits" : [
						{"ref" : "TA", "variation" : 0},
						{"ref" : "TC", "variation" : 0},
						{"ref" : "TD", "variation" : 0},
						{"ref" : "TH", "variation" : 0}
					],
		"type" : "CHI"
	},

	{
		"ref" : "TJ",
		"charges" : [],
		"produits" : [],
		"type" : "INF"
	},

	{
		"ref" : "TN",
		"charges" : [
						{"ref" : "RE", "variation" : 0},
						{"ref" : "RH", "variation" : 1},
						{"ref" : "RI", "variation" : 0},
						{"ref" : "RJ", "variation" : 0},
						{"ref" : "RK", "variation" : 0},
						{"ref" : "RL", "variation" : 0}
					],
		"produits" : [
						{"ref" : "TK", "variation" : 0},
						{"ref" : "TL", "variation" : 0}
					],
		"type" : "VAL"
	},

	{
		"ref" : "TQ",
		"charges" : [
						{"ref" : "RP", "variation" : 0},
						{"ref" : "RQ", "variation" : 0}
					],
		"produits" : [
						{"ref" : "TK", "variation" : 0},
						{"ref" : "TL", "variation" : 0}
					],
		"type" : "EXC"
	},

	{
		"ref" : "TX",
		"charges" : [
						{"ref" : "RW", "variation" : 0}
					],
		"produits" : [
						{"ref" : "TW", "variation" : 0}
					],
		"type" : "RES"
	},

	{
		"ref" : "UG",
		"charges" : [
						{"ref" : "SF", "variation" : 0}
					],
		"produits" : [
						{"ref" : "UF", "variation" : 0}
					],
		"type" : "RES"
	},

	{
		"ref" : "UH",
		"produits" : [
						{"ref" : "UF", "variation" : 0},
						{"ref" : "TW", "variation" : 0}
					],
		"charges" : [],

		"type" : "TOT"
	},	

	{
		"ref" : "UI",
		"charges" : [
						{"ref" : "SH", "variation" : 0}
					],
		"produits" : [
						{"ref" : "UH", "variation" : 0}
					],
		"type" : "RES"
	},	

	{
		"ref" : "UJ",
		"produits" : [],
		"charges" : [],
		"type" : "INF"
	},

	{
		"ref" : "UP",
		"charges" : [
						{"ref" : "SO", "variation" : 0}
					],
		"produits" : [
						{"ref" : "UO", "variation" : 0}
					],
		"type" : "RES"
	},

	{
		"ref" : "UZ",
		"charges" : [
						{"ref" : "ST", "variation" : 0}
					],
		"produits" : [
						{"ref" : "UT", "variation" : 0}
					],
		"type" : "RES"
	},

	{
		"ref" : "SS",
		"charges" : [
						{"ref" : "SR", "variation" : 0},
						{"ref" : "SQ", "variation" : 0}
					],
		"produits" : [],

		"type" : "TOT"
	},

	{
		"ref" : "RW",
		"charges" : [
						{"ref" : "RA", "variation" : 0},
						{"ref" : "RB", "variation" : 1},
						{"ref" : "RC", "variation" : 0},
						{"ref" : "RD", "variation" : 1},
						{"ref" : "RE", "variation" : 0},
						{"ref" : "RH", "variation" : 1},
						{"ref" : "RI", "variation" : 0},
						{"ref" : "RJ", "variation" : 0},
						{"ref" : "RK", "variation" : 0},
						{"ref" : "RL", "variation" : 0},
						{"ref" : "RP", "variation" : 0},
						{"ref" : "RQ", "variation" : 0},
						{"ref" : "RS", "variation" : 0}
					],
		"produits" : [],
		"type" : "TOT"
	},

	{
		"ref" : "SF",
		"charges" : [
						{"ref" : "SA", "variation" : 0},
						{"ref" : "SC", "variation" : 0},
						{"ref" : "SD", "variation" : 0}
					],
		"produits" : [],
		
		"type" : "TOT"
	},

	{
		"ref" : "SH",
		"charges" : [
						{"ref" : "SA", "variation" : 0},
						{"ref" : "SC", "variation" : 0},
						{"ref" : "SD", "variation" : 0},
						{"ref" : "RA", "variation" : 0},
						{"ref" : "RB", "variation" : 1},
						{"ref" : "RC", "variation" : 0},
						{"ref" : "RD", "variation" : 1},
						{"ref" : "RE", "variation" : 0},
						{"ref" : "RH", "variation" : 1},
						{"ref" : "RI", "variation" : 0},
						{"ref" : "RJ", "variation" : 0},
						{"ref" : "RK", "variation" : 0},
						{"ref" : "RL", "variation" : 0},
						{"ref" : "RP", "variation" : 0},
						{"ref" : "RQ", "variation" : 0},
						{"ref" : "RS", "variation" : 0}
					],
		"produits" : [],
		
		"type" : "TOT"
	},

	{"ref" : "SO",
	 "charges" : [{"ref" : "SK", "variation" : 0},{"ref" : "SL", "variation" : 0},{"ref" : "SM", "variation" : 0}],
	 "produits" : [],
	 "type" : "TOT"},

	{
		"ref" : "ST",
		"charges" : [{"ref" : "SA", "variation" : 0},
						{"ref" : "SC", "variation" : 0},
						{"ref" : "SD", "variation" : 0},
						{"ref" : "RA", "variation" : 0},
						{"ref" : "RB", "variation" : 1},
						{"ref" : "RC", "variation" : 0},
						{"ref" : "RD", "variation" : 1},
						{"ref" : "RE", "variation" : 0},
						{"ref" : "RH", "variation" : 1},
						{"ref" : "RI", "variation" : 0},
						{"ref" : "RJ", "variation" : 0},
						{"ref" : "RK", "variation" : 0},
						{"ref" : "RL", "variation" : 0},
						{"ref" : "RP", "variation" : 0},
						{"ref" : "RQ", "variation" : 0},
						{"ref" : "RS", "variation" : 0},
						{"ref" : "SK", "variation" : 0},
						{"ref" : "SL", "variation" : 0},
						{"ref" : "SM", "variation" : 0},
						{"ref" : "SQ", "variation" : 0},
						{"ref" : "SR", "variation" : 0}],
		"produits" : [],
		"type" : "TOT"
	}
]